onnx2torch/__init__.py
onnx2torch/converter.py
onnx2torch/onnx_graph.py
onnx2torch/onnx_node.py
onnx2torch/onnx_tensor.py
onnx2torch/node_converters/__init__.py
onnx2torch/node_converters/activations.py
onnx2torch/node_converters/arg_extrema.py
onnx2torch/node_converters/average_pool.py
onnx2torch/node_converters/base_element_wise.py
onnx2torch/node_converters/batch_norm.py
onnx2torch/node_converters/binary_math_operations.py
onnx2torch/node_converters/cast.py
onnx2torch/node_converters/clip.py
onnx2torch/node_converters/comparisons.py
onnx2torch/node_converters/concat.py
onnx2torch/node_converters/constant.py
onnx2torch/node_converters/constant_of_shape.py
onnx2torch/node_converters/conv.py
onnx2torch/node_converters/cumsum.py
onnx2torch/node_converters/depth_to_space.py
onnx2torch/node_converters/dropout.py
onnx2torch/node_converters/einsum.py
onnx2torch/node_converters/expand.py
onnx2torch/node_converters/eye_like.py
onnx2torch/node_converters/flatten.py
onnx2torch/node_converters/functions.py
onnx2torch/node_converters/gather.py
onnx2torch/node_converters/gemm.py
onnx2torch/node_converters/global_average_pool.py
onnx2torch/node_converters/identity.py
onnx2torch/node_converters/instance_norm.py
onnx2torch/node_converters/isinf.py
onnx2torch/node_converters/isnan.py
onnx2torch/node_converters/layer_norm.py
onnx2torch/node_converters/logical.py
onnx2torch/node_converters/lrn.py
onnx2torch/node_converters/matmul.py
onnx2torch/node_converters/max_pool.py
onnx2torch/node_converters/mean.py
onnx2torch/node_converters/min_max.py
onnx2torch/node_converters/mod.py
onnx2torch/node_converters/neg.py
onnx2torch/node_converters/nms.py
onnx2torch/node_converters/nonzero.py
onnx2torch/node_converters/pad.py
onnx2torch/node_converters/pow.py
onnx2torch/node_converters/range.py
onnx2torch/node_converters/reciprocal.py
onnx2torch/node_converters/reduce.py
onnx2torch/node_converters/registry.py
onnx2torch/node_converters/reshape.py
onnx2torch/node_converters/resize.py
onnx2torch-1.5.15.dist-info/LICENSE
onnx2torch-1.5.15.dist-info/METADATA
onnx2torch-1.5.15.dist-info/WHEEL
onnx2torch-1.5.15.dist-info/top_level.txt
onnx2torch-1.5.15.dist-info/RECORD
