Metadata-Version: 2.1
Name: onnx2torch
Version: 1.5.15
Summary: ONNX to PyTorch converter
Author-email: ENOT LLC <enot@enot.ai>
License: Apache License
Project-URL: homepage, https://enot.ai
Project-URL: repository, https://github.com/ENOT-AutoDL/onnx2torch
Keywords: AI,onnx,torch,onnx2torch,converters
Classifier: Development Status :: 5 - Production/Stable
Classifier: License :: OSI Approved :: Apache Software License
Classifier: Programming Language :: Python
Classifier: Programming Language :: Python :: 3 :: Only
Requires-Python: >=3.6
License-File: LICENSE
Requires-Dist: numpy >=1.16.4
Requires-Dist: onnx >=1.9.0
Requires-Dist: torch >=1.8.0
Requires-Dist: torchvision >=0.9.0
Provides-Extra: dev
Requires-Dist: pytest ; extra == 'dev'
Requires-Dist: black ; extra == 'dev'
Requires-Dist: isort ; extra == 'dev'
Requires-Dist: pylint ; extra == 'dev'
Requires-Dist: pre-commit ; extra == 'dev'
Requires-Dist: onnxruntime ; extra == 'dev'
Requires-Dist: Pillow ; extra == 'dev'
Requires-Dist: requests ; extra == 'dev'
Requires-Dist: googledrivedownloader ; extra == 'dev'
